HQApi/__init__.py
HQApi/__main__.py
HQApi/exceptions.py
HQApi/hq_api.py
HQApi/hq_api_cli.py
HQApi/hq_websocket.py
HQApi-2.5.1.dist-info/LICENSE
HQApi-2.5.1.dist-info/METADATA
HQApi-2.5.1.dist-info/WHEEL
HQApi-2.5.1.dist-info/entry_points.txt
HQApi-2.5.1.dist-info/top_level.txt
HQApi-2.5.1.dist-info/RECORD
