Metadata-Version: 2.1
Name: HQApi
Version: 2.5.1
Summary: HQ Trivia & Words API
Home-page: https://github.com/apipy/HQApi
Author: Katant
Author-email: katant.savelev@yandex.ru
License: UNKNOWN
Platform: UNKNOWN
Classifier: Programming Language :: Python :: 3.8
Classifier: License :: OSI Approved :: GNU General Public License v3 (GPLv3)
Classifier: Operating System :: OS Independent
Requires-Python: >=3.4
Requires-Dist: requests
Requires-Dist: lomond
Requires-Dist: PyJWT
